pyctype/__init__.py
pyctype/_cbuiltin/__init__.py
pyctype/_cerr/__init__.py
pyctype/_ctypes/__init__.py
pyctype/_ctypes/boolean.py
pyctype/_ctypes/char.py
pyctype/_ctypes/ctype.py
pyctype/_ctypes/double.py
pyctype/_ctypes/floats.py
pyctype/_ctypes/ints.py
pyctype/_ctypes/long.py
pyctype/_ctypes/longlong.py
pyctype/_ctypes/ptr.py
pyctype/_ctypes/short.py
pyctype/_ctypes/structs.py
pyctype/_ctypes/typedef.py
pyctype/_ctypes/uint.py
pyctype/_ctypes/ulong.py
pyctype/_ctypes/ulonglong.py
pyctype/_ctypes/ushort.py
pyctype/_ctypes/void.py
pyctype/tests/__init__.py
pyctype-7.4.0.dist-info/METADATA
pyctype-7.4.0.dist-info/WHEEL
pyctype-7.4.0.dist-info/top_level.txt
pyctype-7.4.0.dist-info/RECORD
