Metadata-Version: 2.1
Name: pyctype
Version: 7.4.0
Summary: Interact with cython, python, ctypes, and use other c/c++ tools
Home-page: https://github.com/notepads/ctype
Author: tanket
Author-email: tanket@assurmail.net
Classifier: Programming Language :: Python :: 3
Classifier: License :: OSI Approved :: MIT License
Classifier: Operating System :: OS Independent
